oxiz/__init__.py
oxiz/oxiz.cpython-314-x86_64-linux-gnu.so
oxiz-0.1.2.dist-info/METADATA
oxiz-0.1.2.dist-info/WHEEL
oxiz-0.1.2.dist-info/RECORD
