Metadata-Version: 2.4
Name: oxiz
Version: 0.1.2
Classifier: Programming Language :: Rust
Classifier: Programming Language :: Python :: Implementation :: CPython
Classifier: Programming Language :: Python :: Implementation :: PyPy
Classifier: Programming Language :: Python :: 3
Classifier: Programming Language :: Python :: 3.8
Classifier: Programming Language :: Python :: 3.9
Classifier: Programming Language :: Python :: 3.10
Classifier: Programming Language :: Python :: 3.11
Classifier: Programming Language :: Python :: 3.12
Classifier: Development Status :: 4 - Beta
Classifier: Intended Audience :: Science/Research
Classifier: Intended Audience :: Developers
Classifier: Topic :: Scientific/Engineering
Classifier: Topic :: Scientific/Engineering :: Mathematics
Classifier: License :: OSI Approved :: MIT License
Classifier: License :: OSI Approved :: Apache Software License
Summary: Python bindings for OxiZ SMT Solver
Keywords: smt,solver,sat,verification,logic,theorem-prover
License: MIT OR Apache-2.0
Requires-Python: >=3.8
Project-URL: Documentation, https://docs.rs/oxiz
Project-URL: Homepage, https://github.com/cool-japan/oxiz
Project-URL: Repository, https://github.com/cool-japan/oxiz
